biliup/Danmaku/__init__.py
biliup/Danmaku/bilibili.py
biliup/Danmaku/douyin.py
biliup/Danmaku/douyin_util/__init__.py
biliup/Danmaku/douyin_util/dy.proto
biliup/Danmaku/douyin_util/dy_pb2.py
biliup/Danmaku/douyin_util/dy_pb2.pyi
biliup/Danmaku/douyin_util/get_signature_test.py
biliup/Danmaku/douyin_util/webmssdk.js
biliup/Danmaku/douyu.py
biliup/Danmaku/huya.py
biliup/Danmaku/paramgen/__init__.py
biliup/Danmaku/paramgen/arcparam.py
biliup/Danmaku/paramgen/enc.py
biliup/Danmaku/paramgen/liveparam.py
biliup/Danmaku/twitcasting.py
biliup/Danmaku/twitch.py
biliup/Danmaku/youtube.py
biliup/__init__.py
biliup/__main__.py
biliup/app.py
biliup/common/Daemon.py
biliup/common/__init__.py
biliup/common/configlog.ini
biliup/common/log.py
biliup/common/reload.py
biliup/common/tars/EndpointF.py
biliup/common/tars/QueryF.py
biliup/common/tars/__TimeoutQueue.py
biliup/common/tars/__adapterproxy.py
biliup/common/tars/__async.py
biliup/common/tars/__init__.py
biliup/common/tars/__logger.py
biliup/common/tars/__packet.py
biliup/common/tars/__rpc.py
biliup/common/tars/__servantproxy.py
biliup/common/tars/__tars.py
biliup/common/tars/__trans.py
biliup/common/tars/__tup.py
biliup/common/tars/__util.py
biliup/common/tars/core.py
biliup/common/tars/exception.py
biliup/common/tars/tars/EndpointF.tars
biliup/common/tars/tars/QueryF.tars
biliup/common/tars/tars/__init__.py
biliup/common/timer.py
biliup/common/tools.py
biliup/common/util.py
biliup/config.py
biliup/database/__init__.py
biliup/database/db.py
biliup/database/migration/env.py
biliup/database/migration/script.py.mako
biliup/database/models.py
biliup/downloader.py
biliup/engine/__init__.py
biliup/engine/decorators.py
biliup/engine/download.py
biliup/engine/event.py
biliup/engine/sync_downloader.py
biliup/engine/upload.py
biliup/handler.py
biliup/plugins/__init__.py
biliup/plugins/acfun.py
biliup/plugins/afreecaTV.py
biliup/plugins/bigo.py
biliup/plugins/bili_chromeup.py
biliup/plugins/bili_webup.py
biliup/plugins/bili_webup_sync.py
biliup_mysql-1.0.8.post1.dist-info/METADATA
biliup_mysql-1.0.8.post1.dist-info/WHEEL
biliup_mysql-1.0.8.post1.dist-info/entry_points.txt
biliup_mysql-1.0.8.post1.dist-info/licenses/LICENSE
biliup_mysql-1.0.8.post1.dist-info/RECORD
